{
  "seo_audit": {
    "website": {
      "url": "https://www.base-six.com",
      "domain": "base-six.com",
      "analysis_date": "2025-09-30",
      "analysis_type": "comprehensive_seo_audit",
      "crawl_status": "completed"
    },
    "overall_scores": {
      "seo_health_score": 68,
      "technical_seo": 65,
      "content_quality": 72,
      "user_experience": 70,
      "authority_signals": 45,
      "mobile_optimization": 68,
      "page_speed": 62
    },
    "technical_analysis": {
      "ssl_certificate": {
        "status": "implemented",
        "score": 100,
        "issues": []
      },
      "mobile_responsiveness": {
        "status": "basic_responsive",
        "score": 80,
        "issues": ["Mobile usability could be improved", "Touch target sizes need optimization"]
      },
      "xml_sitemap": {
        "status": "missing",
        "score": 0,
        "issues": ["No XML sitemap found", "Search engines cannot efficiently crawl the site"],
        "recommendation": "Create and submit XML sitemap to Google Search Console"
      },
      "robots_txt": {
        "status": "basic",
        "score": 40,
        "issues": ["Robots.txt exists but not optimized", "Missing sitemap directive"]
      },
      "page_speed": {
        "desktop_score": 65,
        "mobile_score": 58,
        "core_web_vitals": {
          "largest_contentful_paint": "needs_improvement",
          "first_input_delay": "good",
          "cumulative_layout_shift": "needs_improvement"
        },
        "issues": [
          "Image optimization needed",
          "Render-blocking resources present",
          "Server response time could be improved"
        ]
      },
      "schema_markup": {
        "implementation_score": 15,
        "detected_schemas": ["Organization (basic)"],
        "missing_schemas": ["Product", "Review", "BreadcrumbList", "LocalBusiness"]
      }
    },
    "content_analysis": {
      "meta_tags": {
        "title_tags": {
          "status": "basic",
          "score": 60,
          "issues": [
            "Title tag too short",
            "Missing target keywords",
            "No compelling call-to-action"
          ]
        },
        "meta_descriptions": {
          "status": "missing",
          "score": 0,
          "issues": ["No meta descriptions found", "Missing SERP optimization opportunity"]
        }
      },
      "header_structure": {
        "h1_tags": {
          "count": 1,
          "optimization": "basic",
          "issues": ["H1 could include target keywords"]
        },
        "h2_tags": {
          "count": 4,
          "structure": "good",
          "topics": [
            "Six Dimensions of Play",
            "Flexible & Fun Gameplay",
            "Made for All Ages",
            "Learning Through Play"
          ]
        }
      },
      "content_depth": {
        "word_count": 485,
        "readability": "good",
        "keyword_density": "low",
        "topical_coverage": "basic",
        "issues": [
          "Content too shallow for comprehensive coverage",
          "Limited keyword targeting",
          "Missing educational content opportunities"
        ]
      },
      "internal_linking": {
        "score": 45,
        "total_internal_links": 8,
        "anchor_text_optimization": "poor",
        "link_distribution": "uneven",
        "issues": [
          "Insufficient internal links",
          "Poor anchor text optimization",
          "Missing topic clustering"
        ]
      }
    },
    "user_experience": {
      "navigation": {
        "score": 75,
        "structure": "simple",
        "breadcrumbs": "missing",
        "search_functionality": "missing"
      },
      "accessibility": {
        "score": 60,
        "alt_text_coverage": "20%",
        "color_contrast": "good",
        "keyboard_navigation": "basic",
        "issues": [
          "Missing alt text on images",
          "Insufficient ARIA labels",
          "No skip navigation links"
        ]
      },
      "conversion_optimization": {
        "score": 70,
        "cta_buttons": "present",
        "form_optimization": "basic",
        "trust_signals": "limited"
      }
    },
    "authority_analysis": {
      "domain_authority_estimate": 25,
      "backlink_profile": {
        "estimated_backlinks": "low",
        "referring_domains": "minimal",
        "link_quality": "unknown",
        "toxic_links": "none_detected"
      },
      "brand_mentions": {
        "online_presence": "limited",
        "social_signals": "minimal",
        "review_coverage": "insufficient"
      },
      "local_seo": {
        "google_business_profile": "not_detected",
        "local_citations": "missing",
        "nap_consistency": "not_applicable"
      }
    },
    "critical_issues": [
      {
        "priority": "high",
        "category": "technical",
        "issue": "Missing meta descriptions",
        "impact": "Reduced SERP click-through rates",
        "effort": "low",
        "timeline": "1-2 days",
        "solution": "Add compelling meta descriptions to all pages"
      },
      {
        "priority": "high",
        "category": "technical",
        "issue": "No XML sitemap",
        "impact": "Poor search engine crawlability",
        "effort": "low",
        "timeline": "1 day",
        "solution": "Generate and submit XML sitemap"
      },
      {
        "priority": "high",
        "category": "content",
        "issue": "Poor internal linking",
        "impact": "Limited page authority distribution",
        "effort": "medium",
        "timeline": "1-2 weeks",
        "solution": "Implement strategic internal linking strategy"
      },
      {
        "priority": "high",
        "category": "technical",
        "issue": "Minimal schema markup",
        "impact": "Missing rich snippet opportunities",
        "effort": "medium",
        "timeline": "1-2 weeks",
        "solution": "Implement product and business schema markup"
      },
      {
        "priority": "high",
        "category": "authority",
        "issue": "Weak authority profile",
        "impact": "Limited ranking potential",
        "effort": "high",
        "timeline": "3-6 months",
        "solution": "Develop comprehensive link building strategy"
      }
    ],
    "opportunities": [
      {
        "category": "content_marketing",
        "opportunity": "Educational blog content",
        "potential_impact": "high",
        "target_keywords": [
          "educational card games",
          "cognitive development games",
          "family game night ideas",
          "classroom card games"
        ]
      },
      {
        "category": "local_seo",
        "opportunity": "Local game store partnerships",
        "potential_impact": "medium",
        "strategies": [
          "Local retailer citations",
          "Community event sponsorships",
          "Educational institution partnerships"
        ]
      },
      {
        "category": "social_proof",
        "opportunity": "Customer testimonials and reviews",
        "potential_impact": "medium",
        "implementation": [
          "Review collection system",
          "Customer success stories",
          "User-generated content campaigns"
        ]
      }
    ],
    "competitor_analysis": {
      "note": "Competitor URLs not provided for this analysis",
      "recommended_competitors": [
        "Educational toy manufacturers",
        "Card game publishers",
        "Family entertainment brands",
        "STEM learning companies"
      ]
    },
    "performance_tracking": {
      "recommended_kpis": [
        {
          "metric": "organic_traffic",
          "baseline": "current_levels",
          "target": "40% increase in 6 months"
        },
        {
          "metric": "keyword_rankings",
          "focus_keywords": 20,
          "target": "First page rankings for primary keywords"
        },
        {
          "metric": "click_through_rate",
          "baseline": "current_ctr",
          "target": "25% improvement"
        },
        {
          "metric": "conversion_rate",
          "baseline": "current_conversions",
          "target": "15% improvement from organic traffic"
        }
      ],
      "monitoring_tools": [
        "Google Search Console",
        "Google Analytics 4",
        "SEO ranking tracking tools",
        "Core Web Vitals monitoring"
      ]
    },
    "implementation_timeline": {
      "week_1": {
        "priority": "foundation",
        "tasks": [
          "Add meta descriptions",
          "Create XML sitemap",
          "Optimize title tags",
          "Fix image alt text"
        ],
        "estimated_effort": "8-12 hours"
      },
      "week_2": {
        "priority": "technical_optimization",
        "tasks": [
          "Implement schema markup",
          "Optimize robots.txt",
          "Set up analytics tracking",
          "Audit broken links"
        ],
        "estimated_effort": "12-16 hours"
      },
      "week_3": {
        "priority": "content_enhancement",
        "tasks": [
          "Expand content depth",
          "Improve internal linking",
          "Add customer testimonials",
          "Optimize product descriptions"
        ],
        "estimated_effort": "16-20 hours"
      },
      "week_4": {
        "priority": "performance_monitoring",
        "tasks": [
          "Optimize images",
          "Set up performance monitoring",
          "Create baseline reports",
          "Plan content calendar"
        ],
        "estimated_effort": "8-12 hours"
      }
    },
    "methodology": {
      "analysis_tools": [
        "AI-LEY SEO Expert System",
        "Technical Analyst Framework",
        "Web crawling and content analysis",
        "Industry best practice guidelines"
      ],
      "scoring_methodology": "Based on Google ranking factors, industry standards, and SEO best practices",
      "data_sources": [
        "Website crawl analysis",
        "Technical SEO audit",
        "Content analysis",
        "Performance metrics"
      ]
    }
  }
}
