{
  "entrypoints": [
    "main"
  ],
  "origins": {
    "214": [
      249,
      401,
      643,
      785,
      869,
      214
    ],
    "237": [
      237
    ],
    "785": [
      214,
      249,
      643,
      869,
      785
    ],
    "17896441": [
      214,
      869,
      401
    ],
    "main": [
      354,
      869,
      792
    ],
    "runtime~main": [
      792,
      869,
      354
    ],
    "0058b4c6": [
      849
    ],
    "0d8d294e": [
      301
    ],
    "0e384e19": [
      976
    ],
    "1df93b7f": [
      869,
      583
    ],
    "36994c47": [
      858
    ],
    "5e95c892": [
      647
    ],
    "814f3328": [
      472
    ],
    "81a20b72": [
      118
    ],
    "9e4087bc": [
      711
    ],
    "a4040f6e": [
      613
    ],
    "a6aa9e1f": [
      214,
      785,
      869,
      643
    ],
    "a7456010": [
      235
    ],
    "a7bd4aaa": [
      98
    ],
    "a94703ab": [
      869,
      48
    ],
    "aba21aa0": [
      742
    ],
    "acecf23e": [
      903
    ],
    "b7eb4dec": [
      367
    ],
    "c15d9823": [
      146
    ],
    "ccc49370": [
      214,
      785,
      869,
      249
    ],
    "d589d3a7": [
      924
    ],
    "f81c1134": [
      130
    ],
    "styles": [
      48,
      214,
      249,
      354,
      401,
      583,
      643,
      785,
      792,
      869
    ]
  },
  "assets": {
    "48": {
      "js": [
        {
          "file": "assets/js/a94703ab.bbf5fab3.js",
          "hash": "56c48f9e05050168",
          "publicPath": "/assets/js/a94703ab.bbf5fab3.js"
        }
      ]
    },
    "98": {
      "js": [
        {
          "file": "assets/js/a7bd4aaa.3780061d.js",
          "hash": "32e9d109cd0fa0ed",
          "publicPath": "/assets/js/a7bd4aaa.3780061d.js"
        }
      ]
    },
    "118": {
      "js": [
        {
          "file": "assets/js/81a20b72.df761a66.js",
          "hash": "273ecb280cc62c4b",
          "publicPath": "/assets/js/81a20b72.df761a66.js"
        }
      ]
    },
    "130": {
      "js": [
        {
          "file": "assets/js/f81c1134.d7bdc7e9.js",
          "hash": "b60ef50e9fc86844",
          "publicPath": "/assets/js/f81c1134.d7bdc7e9.js"
        }
      ]
    },
    "146": {
      "js": [
        {
          "file": "assets/js/c15d9823.edec98ff.js",
          "hash": "89d6696d3667afd8",
          "publicPath": "/assets/js/c15d9823.edec98ff.js"
        }
      ]
    },
    "214": {
      "js": [
        {
          "file": "assets/js/214.58c0704e.js",
          "hash": "6b036dd6f720c6f1",
          "publicPath": "/assets/js/214.58c0704e.js"
        }
      ]
    },
    "235": {
      "js": [
        {
          "file": "assets/js/a7456010.bcafcff4.js",
          "hash": "ed8a450e90a9b5a8",
          "publicPath": "/assets/js/a7456010.bcafcff4.js"
        }
      ]
    },
    "237": {
      "js": [
        {
          "file": "assets/js/237.6b5c8f3f.js",
          "hash": "65afdb05fe0396ef",
          "publicPath": "/assets/js/237.6b5c8f3f.js"
        }
      ]
    },
    "249": {
      "js": [
        {
          "file": "assets/js/ccc49370.2d54edd9.js",
          "hash": "c7dbbb7b6f206b0a",
          "publicPath": "/assets/js/ccc49370.2d54edd9.js"
        }
      ]
    },
    "301": {
      "js": [
        {
          "file": "assets/js/0d8d294e.2df8536f.js",
          "hash": "523cd786e05ad54f",
          "publicPath": "/assets/js/0d8d294e.2df8536f.js"
        }
      ]
    },
    "354": {
      "js": [
        {
          "file": "assets/js/runtime~main.a85f096d.js",
          "hash": "8d7b98fd38179acb",
          "publicPath": "/assets/js/runtime~main.a85f096d.js"
        }
      ]
    },
    "367": {
      "js": [
        {
          "file": "assets/js/b7eb4dec.72e47d28.js",
          "hash": "faa348e579b4d9d1",
          "publicPath": "/assets/js/b7eb4dec.72e47d28.js"
        }
      ]
    },
    "401": {
      "js": [
        {
          "file": "assets/js/17896441.cc44c218.js",
          "hash": "3967963aa020927e",
          "publicPath": "/assets/js/17896441.cc44c218.js"
        }
      ]
    },
    "472": {
      "js": [
        {
          "file": "assets/js/814f3328.da015f33.js",
          "hash": "5a95f4bc15c8216e",
          "publicPath": "/assets/js/814f3328.da015f33.js"
        }
      ]
    },
    "583": {
      "js": [
        {
          "file": "assets/js/1df93b7f.efb35083.js",
          "hash": "f91dbc9752f8e037",
          "publicPath": "/assets/js/1df93b7f.efb35083.js"
        }
      ]
    },
    "613": {
      "js": [
        {
          "file": "assets/js/a4040f6e.d30651f2.js",
          "hash": "94c38c52bd484a20",
          "publicPath": "/assets/js/a4040f6e.d30651f2.js"
        }
      ]
    },
    "643": {
      "js": [
        {
          "file": "assets/js/a6aa9e1f.5811ac7a.js",
          "hash": "d8381e3954bd57b3",
          "publicPath": "/assets/js/a6aa9e1f.5811ac7a.js"
        }
      ]
    },
    "647": {
      "js": [
        {
          "file": "assets/js/5e95c892.69644762.js",
          "hash": "c713a4cbcb276641",
          "publicPath": "/assets/js/5e95c892.69644762.js"
        }
      ]
    },
    "711": {
      "js": [
        {
          "file": "assets/js/9e4087bc.a385998e.js",
          "hash": "d8ced6e134652ef5",
          "publicPath": "/assets/js/9e4087bc.a385998e.js"
        }
      ]
    },
    "742": {
      "js": [
        {
          "file": "assets/js/aba21aa0.22430ce3.js",
          "hash": "302e33b19e90b60d",
          "publicPath": "/assets/js/aba21aa0.22430ce3.js"
        }
      ]
    },
    "785": {
      "js": [
        {
          "file": "assets/js/785.2e2ffe30.js",
          "hash": "d49c3b1917b114a8",
          "publicPath": "/assets/js/785.2e2ffe30.js"
        }
      ]
    },
    "792": {
      "js": [
        {
          "file": "assets/js/main.11ec0f2e.js",
          "hash": "21b89e285f198718",
          "publicPath": "/assets/js/main.11ec0f2e.js"
        }
      ]
    },
    "849": {
      "js": [
        {
          "file": "assets/js/0058b4c6.44c86810.js",
          "hash": "6b6c5985c2c1007c",
          "publicPath": "/assets/js/0058b4c6.44c86810.js"
        }
      ]
    },
    "858": {
      "js": [
        {
          "file": "assets/js/36994c47.b6a7b7d0.js",
          "hash": "40a54a6aedf4f132",
          "publicPath": "/assets/js/36994c47.b6a7b7d0.js"
        }
      ]
    },
    "869": {
      "css": [
        {
          "file": "assets/css/styles.e8904506.css",
          "hash": "4102b226f1920687",
          "publicPath": "/assets/css/styles.e8904506.css"
        }
      ]
    },
    "903": {
      "js": [
        {
          "file": "assets/js/acecf23e.ef699d67.js",
          "hash": "ddddd56365347f45",
          "publicPath": "/assets/js/acecf23e.ef699d67.js"
        }
      ]
    },
    "924": {
      "js": [
        {
          "file": "assets/js/d589d3a7.670f0a59.js",
          "hash": "b0d247a800e714d5",
          "publicPath": "/assets/js/d589d3a7.670f0a59.js"
        }
      ]
    },
    "976": {
      "js": [
        {
          "file": "assets/js/0e384e19.bac8903b.js",
          "hash": "888e128bcbc4508d",
          "publicPath": "/assets/js/0e384e19.bac8903b.js"
        }
      ]
    }
  }
}